[
  {
    "id": 1,
    "name": "Sample Paint Bucket",
    "description": "This is a sample product description.",
    "price": "2500",
    "category": "Paints",
    "brand": "WAPP",
    "image": "https://via.placeholder.com/300"
  },
  {
    "id": 1763882691187,
    "name": "sffdsfds",
    "category": "Paints",
    "brand": "WAPP",
    "price": "8000",
    "description": "cdscscdc",
    "image": "https://res.cloudinary.com/dzku6byci/image/upload/v1763882690/hxvall7io8d9z2rpi2xc.jpg"
  },
  {
    "id": 1763913091201,
    "name": "EMULSION BRILLIANT WHITE 20L",
    "category": "Paints",
    "brand": "JAT",
    "price": "13800",
    "description": "Product Details Of WHITE by JAT Interior Emulsion :- \n * Coverage up to 225 sq. Feet per Litre.\n * Touch dry in 15-30 minutes.\n * Can be recoated in 2-4 hours.\n * Can be applied with a brush or roller.\n * Can be diluted up to 50% of water by volume of paint.",
    "image": "https://res.cloudinary.com/dzku6byci/image/upload/v1763913090/qxberimz6gcgsmrl7u82.jpg"
  }
]